cellshape_cloud/__init__.py
cellshape_cloud/cloud_autoencoder.py
cellshape_cloud/extract.py
cellshape_cloud/extract_features.py
cellshape_cloud/helper_modules.py
cellshape_cloud/lightning_autoencoder.py
cellshape_cloud/lightning_classifier.py
cellshape_cloud/main.py
cellshape_cloud/plotting.py
cellshape_cloud/pointcloud_dataset.py
cellshape_cloud/reports.py
cellshape_cloud/simclr_dataset.py
cellshape_cloud/train_autoencoder.py
cellshape_cloud/training_functions.py
cellshape_cloud/transformations.py
cellshape_cloud/vendor/__init__.py
cellshape_cloud/vendor/chamfer_distance.py
cellshape_cloud/vendor/decoders.py
cellshape_cloud/vendor/encoders.py
cellshape_cloud/vendor/graph_functions.py
tests/__init__.py
tests/test_integration/__init__.py
tests/test_unit/__init__.py
tests/test_unit/test_placeholder.py
cellshape_cloud-0.1.3.dist-info/LICENSE
cellshape_cloud-0.1.3.dist-info/METADATA
cellshape_cloud-0.1.3.dist-info/WHEEL
cellshape_cloud-0.1.3.dist-info/top_level.txt
cellshape_cloud-0.1.3.dist-info/RECORD
