Metadata-Version: 2.1
Name: cellshape-cloud
Version: 0.1.3
Summary: 3D cell shape analysis using geometric deep learning on point clouds
Author: Matt De Vries, Lucas Dent, Adam Tyson
Author-email: mattdevries.ai@gmail.com
Project-URL: Source Code, https://github.com/Sentinal4D/cellshape-cloud
Project-URL: Bug Tracker, https://github.com/Sentinal4D/cellshape-cloud/issues
Classifier: Development Status :: 3 - Alpha
Classifier: Operating System :: POSIX :: Linux
Classifier: Operating System :: Microsoft :: Windows :: Windows 10
Classifier: Programming Language :: Python
Classifier: Programming Language :: Python :: 3.7
Classifier: Programming Language :: Python :: 3.8
Classifier: Programming Language :: Python :: 3.9
Classifier: Topic :: Scientific/Engineering :: Image Recognition
Classifier: Intended Audience :: Developers
Classifier: Intended Audience :: Science/Research
Requires-Python: >=3.7
License-File: LICENSE
Requires-Dist: torch
Requires-Dist: torchvision
Requires-Dist: pyntcloud
Requires-Dist: numpy
Requires-Dist: matplotlib
Requires-Dist: tqdm
Requires-Dist: datetime
Requires-Dist: umap-learn
Requires-Dist: scikit-learn
Requires-Dist: tensorboard
Requires-Dist: h5py
Provides-Extra: dev
Requires-Dist: black ; extra == 'dev'
Requires-Dist: black[jupyter] ; extra == 'dev'
Requires-Dist: pytest-cov ; extra == 'dev'
Requires-Dist: pytest ; extra == 'dev'
Requires-Dist: gitpython ; extra == 'dev'
Requires-Dist: coverage (>=5.0.3) ; extra == 'dev'
Requires-Dist: bump2version ; extra == 'dev'
Requires-Dist: pre-commit ; extra == 'dev'
Requires-Dist: flake8 ; extra == 'dev'
